generic_producer/GenericProducer.py
generic_producer/__init__.py
generic_producer-0.0.1.dist-info/LICENSE
generic_producer-0.0.1.dist-info/METADATA
generic_producer-0.0.1.dist-info/WHEEL
generic_producer-0.0.1.dist-info/top_level.txt
generic_producer-0.0.1.dist-info/RECORD
