Metadata-Version: 2.1
Name: generic_producer
Version: 0.0.1
Summary: For sending events to kafka topic.
Home-page: 
Author: Clinton Aghedo
Author-email: aghedoclinton76@gmail.com
Classifier: Programming Language :: Python :: 3
Classifier: License :: OSI Approved :: MIT License
Classifier: Operating System :: OS Independent
Requires-Python: >=3.8
License-File: LICENSE
